[
null,
{"id":1,"expanded":false,"name":"Worldmap","order":37,"parentId":0,"scrollX":811,"scrollY":2019},
{"id":2,"expanded":true,"name":"Leonardo's castle","order":38,"parentId":0,"scrollX":819,"scrollY":461},
{"id":3,"expanded":true,"name":"poe","order":39,"parentId":2,"scrollX":832,"scrollY":640},
{"id":4,"expanded":true,"name":"Begin","order":1,"parentId":0,"scrollX":819,"scrollY":461},
{"id":5,"expanded":false,"name":"poe2","order":40,"parentId":3,"scrollX":811,"scrollY":739},
{"id":6,"expanded":false,"name":"Slaapkamer","order":6,"parentId":8,"scrollX":819,"scrollY":461},
{"id":7,"expanded":false,"name":"Troonkamer","order":7,"parentId":8,"scrollX":811,"scrollY":461},
{"id":8,"expanded":true,"name":"Castle","order":5,"parentId":0,"scrollX":819,"scrollY":461},
{"id":9,"expanded":true,"name":"Sacred cave","order":9,"parentId":8,"scrollX":819,"scrollY":461},
{"id":10,"expanded":true,"name":"Openvelden","order":17,"parentId":0,"scrollX":819,"scrollY":461},
{"id":11,"expanded":false,"name":"poe3","order":41,"parentId":3,"scrollX":811,"scrollY":739},
{"id":12,"expanded":true,"name":"Openvelden","order":18,"parentId":10,"scrollX":816,"scrollY":1760},
{"id":13,"expanded":true,"name":"Openvelden 3 (dorp)","order":23,"parentId":10,"scrollX":811,"scrollY":507},
{"id":14,"expanded":false,"name":"Huis 2","order":25,"parentId":13,"scrollX":819,"scrollY":461},
{"id":15,"expanded":false,"name":"Huis 3","order":26,"parentId":13,"scrollX":819,"scrollY":461},
{"id":16,"expanded":false,"name":"Huis 1","order":24,"parentId":13,"scrollX":819,"scrollY":461},
{"id":17,"expanded":false,"name":"Herberg","order":27,"parentId":13,"scrollX":819,"scrollY":461},
{"id":18,"expanded":false,"name":"Keuken","order":8,"parentId":8,"scrollX":819,"scrollY":461},
{"id":19,"expanded":true,"name":"Cave of doom","order":19,"parentId":12,"scrollX":811,"scrollY":739},
{"id":20,"expanded":false,"name":"-1","order":20,"parentId":19,"scrollX":811,"scrollY":480},
{"id":21,"expanded":false,"name":"-2","order":21,"parentId":19,"scrollX":1589,"scrollY":454},
{"id":22,"expanded":false,"name":"SC1","order":10,"parentId":9,"scrollX":811,"scrollY":739},
{"id":23,"expanded":false,"name":"SC4","order":14,"parentId":9,"scrollX":2213,"scrollY":453},
{"id":24,"expanded":false,"name":"poe4","order":42,"parentId":3,"scrollX":811,"scrollY":517},
{"id":25,"expanded":false,"name":"SC2","order":11,"parentId":9,"scrollX":811,"scrollY":1467},
null,
{"id":27,"expanded":false,"name":"Amina's magic Inc.","order":35,"parentId":31,"scrollX":819,"scrollY":461},
{"id":28,"expanded":false,"name":"SC5","order":15,"parentId":9,"scrollX":811,"scrollY":461},
{"id":29,"expanded":false,"name":"SC6","order":16,"parentId":9,"scrollX":811,"scrollY":1219},
{"id":30,"expanded":true,"name":"Dragdorp","order":28,"parentId":0,"scrollX":1092,"scrollY":614.6666666666666},
{"id":31,"expanded":true,"name":"Dragvillage","order":31,"parentId":30,"scrollX":1081,"scrollY":1545},
{"id":32,"expanded":false,"name":"RTDP1","order":29,"parentId":30,"scrollX":1182,"scrollY":816},
{"id":33,"expanded":false,"name":"RTDP2","order":30,"parentId":30,"scrollX":811,"scrollY":499},
{"id":34,"expanded":false,"name":"poe5","order":43,"parentId":3,"scrollX":811,"scrollY":480},
{"id":35,"expanded":false,"name":"Inn","order":33,"parentId":31,"scrollX":811,"scrollY":461},
{"id":36,"expanded":false,"name":"Huis 1","order":34,"parentId":31,"scrollX":819,"scrollY":461},
{"id":37,"expanded":false,"name":"Shop","order":32,"parentId":31,"scrollX":811,"scrollY":499},
{"id":38,"expanded":false,"name":"Colosseum","order":36,"parentId":30,"scrollX":819,"scrollY":461},
{"id":39,"expanded":false,"name":"boss chalange","order":97,"parentId":100,"scrollX":819,"scrollY":461},
{"id":40,"expanded":false,"name":"poe6","order":44,"parentId":3,"scrollX":811,"scrollY":979},
{"id":41,"expanded":true,"name":"SC3","order":12,"parentId":9,"scrollX":1318.6666666666667,"scrollY":604},
{"id":42,"expanded":true,"name":"Castle","order":45,"parentId":2,"scrollX":811,"scrollY":739},
{"id":43,"expanded":true,"name":"Centralcity","order":55,"parentId":0,"scrollX":811,"scrollY":979},
{"id":44,"expanded":false,"name":"Troonkamer","order":46,"parentId":42,"scrollX":819,"scrollY":461},
{"id":45,"expanded":false,"name":"Kerker","order":47,"parentId":42,"scrollX":819,"scrollY":461},
{"id":46,"expanded":false,"name":"Kerkergang","order":48,"parentId":42,"scrollX":819,"scrollY":461},
{"id":47,"expanded":false,"name":"Linkergang","order":49,"parentId":42,"scrollX":819,"scrollY":461},
{"id":48,"expanded":false,"name":"Sparkroom","order":50,"parentId":42,"scrollX":811,"scrollY":461},
{"id":49,"expanded":false,"name":"-3","order":22,"parentId":19,"scrollX":821,"scrollY":454},
{"id":50,"expanded":false,"name":"SC Bonusmap","order":13,"parentId":41,"scrollX":832,"scrollY":640},
null,
{"id":52,"expanded":true,"name":"East","order":56,"parentId":43,"scrollX":811,"scrollY":787},
{"id":53,"expanded":false,"name":"Shop","order":65,"parentId":61,"scrollX":811,"scrollY":499},
{"id":54,"expanded":true,"name":"West","order":60,"parentId":43,"scrollX":811,"scrollY":461},
{"id":55,"expanded":false,"name":"Roodhuis","order":57,"parentId":52,"scrollX":819,"scrollY":461},
{"id":56,"expanded":false,"name":"Blauwhuis","order":58,"parentId":52,"scrollX":819,"scrollY":461},
{"id":57,"expanded":false,"name":"Groenhuis","order":59,"parentId":52,"scrollX":304,"scrollY":224},
{"id":58,"expanded":false,"name":"Roodhuis","order":61,"parentId":54,"scrollX":819,"scrollY":461},
{"id":59,"expanded":false,"name":"Blauwhuis","order":62,"parentId":54,"scrollX":819,"scrollY":461},
{"id":60,"expanded":false,"name":"Groenhuis","order":63,"parentId":54,"scrollX":819,"scrollY":461},
{"id":61,"expanded":true,"name":"Centralroad","order":64,"parentId":43,"scrollX":811,"scrollY":651},
{"id":62,"expanded":true,"name":"Sandabestuur","order":66,"parentId":61,"scrollX":811,"scrollY":461},
{"id":63,"expanded":false,"name":"Salon","order":68,"parentId":61,"scrollX":819,"scrollY":461},
{"id":64,"expanded":false,"name":"1e verdieping","order":67,"parentId":62,"scrollX":819,"scrollY":461},
{"id":65,"expanded":true,"name":"Abandoned mine","order":69,"parentId":0,"scrollX":811,"scrollY":499},
{"id":66,"expanded":false,"name":"Machineroom","order":54,"parentId":73,"scrollX":811,"scrollY":499},
{"id":67,"expanded":false,"name":"1","order":70,"parentId":65,"scrollX":811,"scrollY":800},
{"id":68,"expanded":false,"name":"2","order":71,"parentId":65,"scrollX":1280,"scrollY":640},
{"id":69,"expanded":false,"name":"3","order":72,"parentId":65,"scrollX":2220,"scrollY":868},
{"id":70,"expanded":false,"name":"4","order":73,"parentId":65,"scrollX":811,"scrollY":461},
{"id":71,"expanded":false,"name":"Rechtergang","order":51,"parentId":42,"scrollX":819,"scrollY":461},
{"id":72,"expanded":false,"name":"Rocketroom","order":52,"parentId":42,"scrollX":811,"scrollY":739},
{"id":73,"expanded":true,"name":"Rocket","order":53,"parentId":2,"scrollX":811,"scrollY":979},
{"id":74,"expanded":true,"name":"Spaceruins","order":74,"parentId":0,"scrollX":811,"scrollY":1123},
{"id":75,"expanded":false,"name":"1","order":75,"parentId":74,"scrollX":811,"scrollY":800},
{"id":76,"expanded":false,"name":"2","order":76,"parentId":74,"scrollX":811,"scrollY":868},
{"id":77,"expanded":false,"name":"3","order":77,"parentId":74,"scrollX":1508,"scrollY":453},
{"id":78,"expanded":false,"name":"4","order":78,"parentId":74,"scrollX":2549,"scrollY":453},
{"id":79,"expanded":true,"name":"Forest","order":79,"parentId":0,"scrollX":811,"scrollY":739},
null,
{"id":81,"expanded":false,"name":"1","order":80,"parentId":79,"scrollX":816,"scrollY":640},
{"id":82,"expanded":false,"name":"2","order":81,"parentId":79,"scrollX":1064,"scrollY":640},
{"id":83,"expanded":false,"name":"3","order":82,"parentId":79,"scrollX":816,"scrollY":800},
{"id":84,"expanded":false,"name":"4","order":83,"parentId":79,"scrollX":816,"scrollY":884},
{"id":85,"expanded":false,"name":"5","order":84,"parentId":79,"scrollX":816,"scrollY":800},
{"id":86,"expanded":false,"name":"Forest","order":2,"parentId":4,"scrollX":811,"scrollY":739},
{"id":87,"expanded":false,"name":"Castle","order":3,"parentId":4,"scrollX":819,"scrollY":461},
{"id":88,"expanded":false,"name":"nothing","order":4,"parentId":4,"scrollX":819,"scrollY":461},
{"id":89,"expanded":true,"name":"Final level","order":85,"parentId":0,"scrollX":816,"scrollY":800},
{"id":90,"expanded":true,"name":"1-Snow mountains","order":86,"parentId":89,"scrollX":811,"scrollY":560},
{"id":91,"expanded":false,"name":"2","order":87,"parentId":90,"scrollX":1404,"scrollY":560},
{"id":92,"expanded":false,"name":"3","order":88,"parentId":90,"scrollX":811,"scrollY":800},
{"id":93,"expanded":false,"name":"4","order":89,"parentId":90,"scrollX":811,"scrollY":1456},
{"id":94,"expanded":false,"name":"5","order":90,"parentId":90,"scrollX":811,"scrollY":628},
{"id":95,"expanded":false,"name":"6","order":91,"parentId":90,"scrollX":811,"scrollY":1473},
{"id":96,"expanded":false,"name":"7","order":92,"parentId":90,"scrollX":811,"scrollY":883},
{"id":97,"expanded":true,"name":"Cosmos-1","order":93,"parentId":89,"scrollX":811,"scrollY":2184},
{"id":98,"expanded":false,"name":"2","order":94,"parentId":97,"scrollX":811,"scrollY":884},
{"id":99,"expanded":false,"name":"3","order":95,"parentId":97,"scrollX":1627,"scrollY":453},
{"id":100,"expanded":true,"name":"4","order":96,"parentId":97,"scrollX":811,"scrollY":461}
]